stringstyler-0.2.1.dist-info/METADATA
stringstyler-0.2.1.dist-info/WHEEL
stringstyler-0.2.1.dist-info/entry_points.txt
stringstyler-0.2.1.dist-info/licenses/LICENSE
stringstyler/__init__.py
stringstyler/stringstyler.py
stringstyler-0.2.1.dist-info/RECORD
