Metadata-Version: 2.1
Name: stringstyler
Version: 0.2.1
Summary: Default template for PDM package
Author-Email: numgrade <num@numgrade.com>
License: MIT
Requires-Python: >=3.9
